{
  "home": {
    "title": "ServIt",
    "desc": "სერვის მარკეტი",
    "omw": "სულ მალე",
    "btn": "შექმენი პროდუქტი"
  },
  "about": {
    "title": "ServIt არის სერვისის მარკეტი",
    "desc": "შექმნილი სერვისის პროვაიდერებისა და კონსუმერებისთვის. როდესაც გესაჭიროება გამოცდილი მუშა, ტალანტის მქონე დიზაინერი, თუ ვინმე ვინხ ყოველდღიური დავალებების შესრულებაში დაგეხმარება, ServIt არის აქ თქვეს შორის ხიდის გასადებად. მომხარებლებს ადვილად შეუძლიათ განათავსონ თავიანი სერვისები რომელცათ სხვას სთავაზობენ ან დავალებები რის შესულებაშიც დახმარება სჭირდებათ."
  },
  "footer": {
    "aboutLink": "ჩვენს შესახებ",
    "contactLink": "კონტაქტები",
    "policies": "პოლიტიკა",
    "rights": "© 2024 ServIt. All rights reserved."
  },
  "header": {
    "aboutLink": "ჩვენს შესახებ",
    "tasks": "დავალებები",
    "services": "სერვისები",
    "products": "პროდუქტები",
    "profile": "პროფილი",
    "pricing": "ფასები",
    "home": "მთავარი",
    "logout": "გასვლა",
    "createProduct": "პროდუქტის დამატება"
  },
  "sorter": {
    "options": "სორტირება",
    "prhigh": "ფასი მაღლიდან დაბლა",
    "prlow": "ფასი დაბლიდან მაღლა",
    "trhigh": "დონე მაღლიდან დაბლა",
    "trlow": "დონე დაბლიდან მაღლა"
  },
  "servicesPage": {
    "notFound": "მსგავსი სერვისი ვერ მოიძებნა."
  },
  "serviceID": {
    "contacts": "კონტაქტები:",
    "msg": "გააგზავნეთ მესიჯი"
  },
  "services": {
    "span": "ServIt:",
    "nospan": "ადგილი სადაც უნარები შესაძლებლებობს პოულობენ"
  },
  "products": {
    "products": "პროდუქტები",
    "noProducts": "პროდუქტები ვერ მოიძებნა"
  },
  "productsID": {
    "stock": "რაოდენობა საწყობში",
    "order": "შეკვეთის მინიმალური რაოდენობა",
    "cart": "კალათაში დამატება",
    "buy": "შეიძინეთ",
    "dimensions": "ზომები",
    "width": "სიგანე",
    "height": "სიმაღლე",
    "depth": "სიღრმე"
  },
  "language": {
    "lang": "ENG"
  },
  "profile": {
    "title": "-ს პროფილი",
    "name": "სრული სახელი:",
    "mail": "მეილი:"
  },
  "sub": {
    "title": "ფასები",
    "subtitle": "გააუმჯობესეთ თქვენი გამოწერის დონე უპირატესობების მისაღებად",
    "frequencies": {
      "monthly": "თვიური",
      "annually": "წლიური"
    },
    "priceSuffix": {
      "monthly": "/თვეში",
      "annually": "/წელიწადში"
    },
    "tiers": {
      "junior": {
        "name": "დამწყები",
        "description": "შესანიშნავია მომხმარებლებისთვის, რომლებიც დაინტერესებულნი არიან სერვისების ან დავალებების განთავსებით",
        "features": [
          "სერვისების განთავსების შესაძლებლობა",
          "დავალებების განთავსების შესაძლებლობა",
          "შეუძლია 1 დავალების შესრულება",
          "15% დავალების საკომისიო"
        ],
        "cta": "უფასო გამოყენება"
      },
      "middle": {
        "name": "საშუალო",
        "description": "შესანიშნავია მომხმარებლებისთვის, რომლებიც დაინტერესებულნი არიან თვეში რამდენიმე დავალების შესრულებით",
        "features": [
          "ყველაფერი უფასო პაკეტიდან პლუს",
          "დავალებების სიის პრიორიტეტი",
          "შეუძლია 3 დავალებამდე შესრულება",
          "10% დავალების საკომისიო"
        ],
        "cta": "დაწყება"
      },
      "senior": {
        "name": "უფროსი",
        "description": "შესანიშნავია მომხმარებლებისთვის, რომლებიც დაინტერესებულნი არიან თვეში ბევრი დავალების შესრულებით",
        "features": [
          "ყველაფერი საშუალო პაკეტიდან პლუს",
          "სერვისების სიის პრიორიტეტი",
          "შეუძლია შეუზღუდავი დავალებების შესრულება",
          "8% დავალების საკომისიო"
        ],
        "cta": "დაწყება"
      }
    }
  },
  "payment": {
    "success": "გადახდა წარმატებულია"
  },
  "addPage": {
    "title": "შექმენი პროდუქტი",
    "name": "სახელი",
    "price": "ფასი",
    "category": "კატეგორია",
    "tags": "ტეგები (მძიმის გამოტოვებით)",
    "brand": "ბრენდი",
    "imageURL": "სურათის URL",
    "width": "სიგანე",
    "height": "სიმაღლე",
    "depth": "სიღრმე",
    "weight": "წონა",
    "description": "აღწერა",
    "submit": "დამატება"
  }
}
